natsort_rs-0.1.17.dist-info/METADATA
natsort_rs-0.1.17.dist-info/WHEEL
natsort_rs-0.1.17.dist-info/licenses/LICENSE
natsort_rs/__init__.py
natsort_rs/natsort_rs.cpython-311-x86_64-linux-gnu.so
natsort_rs-0.1.17.dist-info/RECORD
