Metadata-Version: 2.4
Name: natsort-rs
Version: 0.1.17
Classifier: Programming Language :: Rust
Classifier: Programming Language :: Python :: Implementation :: CPython
Classifier: Programming Language :: Python :: 3
Classifier: Programming Language :: Python :: 3.9
Classifier: Programming Language :: Python :: 3.10
Classifier: Programming Language :: Python :: 3.11
Classifier: Programming Language :: Python :: 3.12
Classifier: Programming Language :: Python :: 3.13
Classifier: Programming Language :: Python :: 3.14
License-File: LICENSE
Summary: A blazing fast natural sorting library for Python
Requires-Python: >=3.9
Project-URL: Homepage, https://github.com/valentinstn/natsort-rs
Project-URL: Repository, https://github.com/valentinstn/natsort-rs
Project-URL: Changelog, https://github.com/valentinstn/natsort-rs/blob/main/CHANGELOG.md
